django_fieldsignals-0.8.0.dist-info/licenses/LICENSE
fieldsignals/__init__.py
fieldsignals/py.typed
fieldsignals/signals.py
fieldsignals/tests/__init__.py
fieldsignals/tests/settings.py
fieldsignals/tests/test_signals.py
django_fieldsignals-0.8.0.dist-info/METADATA
django_fieldsignals-0.8.0.dist-info/WHEEL
django_fieldsignals-0.8.0.dist-info/top_level.txt
django_fieldsignals-0.8.0.dist-info/RECORD
