Metadata-Version: 2.4
Name: django-fieldsignals
Version: 0.8.0
Summary: Django signals that fire when specific model fields change
Author-email: Craig de Stigter <craig@destigter.nz>
License: MIT
Project-URL: Homepage, https://github.com/craigds/django-fieldsignals
Project-URL: Repository, https://github.com/craigds/django-fieldsignals
Classifier: Environment :: Web Environment
Classifier: Framework :: Django
Classifier: Framework :: Django :: 4.2
Classifier: Framework :: Django :: 5.2
Classifier: Framework :: Django :: 6.0
Classifier: Intended Audience :: Developers
Classifier: License :: OSI Approved :: MIT License
Classifier: Operating System :: OS Independent
Classifier: Programming Language :: Python :: 3
Classifier: Programming Language :: Python :: 3.8
Classifier: Programming Language :: Python :: 3.10
Classifier: Programming Language :: Python :: 3.12
Classifier: Programming Language :: Python :: 3.13
Classifier: Topic :: Internet :: WWW/HTTP
Classifier: Typing :: Typed
Requires-Python: >=3.8
License-File: LICENSE
Requires-Dist: django>=4.2
Provides-Extra: dev
Requires-Dist: pytest; extra == "dev"
Requires-Dist: ruff; extra == "dev"
Requires-Dist: tox; extra == "dev"
Requires-Dist: tox-uv; extra == "dev"
Dynamic: license-file
